ceonmedia_db/README.md
ceonmedia_db/__init__.py
ceonmedia_db/alembic.ini
ceonmedia_db/constants.py
ceonmedia_db/database.py
ceonmedia_db/errors.py
ceonmedia_db/main.py
ceonmedia_db/py.typed
ceonmedia_db/setup.py
ceonmedia_db/_auth/__init__.py
ceonmedia_db/_auth/_auth_bearer.py
ceonmedia_db/_auth/_auth_handler.py
ceonmedia_db/_auth/security.py
ceonmedia_db/alembic/README
ceonmedia_db/alembic/env.py
ceonmedia_db/alembic/how_to.txt
ceonmedia_db/alembic/script.py.mako
ceonmedia_db/alembic/versions/4cec02cae1c1_baseline.py
ceonmedia_db/alembic/versions/b05758151eac_added_stripe_tbl_and_crud.py
ceonmedia_db/crud/ABOUT.md
ceonmedia_db/crud/__init__.py
ceonmedia_db/crud/_job.py
ceonmedia_db/crud/_project.py
ceonmedia_db/crud/_session.py
ceonmedia_db/crud/access_control.py
ceonmedia_db/crud/job.py
ceonmedia_db/crud/oauth_account.py
ceonmedia_db/crud/project.py
ceonmedia_db/crud/security.py
ceonmedia_db/crud/stripe.py
ceonmedia_db/crud/submission.py
ceonmedia_db/crud/user.py
ceonmedia_db/crud/user_credit.py
ceonmedia_db/models/__init__.py
ceonmedia_db/models/_security.py
ceonmedia_db/models/_user.py
ceonmedia_db/models/access_control.py
ceonmedia_db/models/base.py
ceonmedia_db/models/job.py
ceonmedia_db/models/order.py
ceonmedia_db/models/product.py
ceonmedia_db/models/project.py
ceonmedia_db/models/stripe.py
ceonmedia_db/models/submission.py
ceonmedia_db/models/user.py
ceonmedia_db/models/user_credit.py
ceonmedia_db/schemas/README.md
ceonmedia_db/schemas/__init__.py
ceonmedia_db/schemas/_schemas.py
ceonmedia_db/schemas/access_control.py
ceonmedia_db/schemas/job.py
ceonmedia_db/schemas/project.py
ceonmedia_db/schemas/user.py
ceonmedia_db/tests/__init__.py
ceonmedia_db/tests/_test_users.py
ceonmedia_db/tests/conftest.py
ceonmedia_db/tests/test_crud_access_control.py
ceonmedia_db/tests/test_crud_email_verification_token.py
ceonmedia_db/tests/test_crud_project_create.py
ceonmedia_db/tests/test_crud_user_create.py
ceonmedia_db/tests/test_crud_user_read.py
ceonmedia_db-0.9.1.dist-info/METADATA
ceonmedia_db-0.9.1.dist-info/WHEEL
ceonmedia_db-0.9.1.dist-info/RECORD
