Metadata-Version: 2.4
Name: ceonmedia-db
Version: 0.9.1
Summary: Defines database schema and provides functionality to interact with the database.
Author-email: Dayne Kolk <daynekolk@hotmail.com>
Requires-Python: >=3.11
Requires-Dist: psycopg2-binary>=2.9.10
Requires-Dist: python-dotenv>=1.1.0
Requires-Dist: sqlmodel>=0.0.24
